trading_contracts/__init__.py
trading_contracts/loader.py
trading_contracts-0.2.0.dist-info/METADATA
trading_contracts-0.2.0.dist-info/WHEEL
trading_contracts-0.2.0.dist-info/top_level.txt
trading_contracts-0.2.0.dist-info/RECORD
